{"textures":{"0":"modelengine:entity/aangs","1":"modelengine:entity/182-1827785_views-minecraft-wood-plank-texture","2":"modelengine:entity/metal","3":"modelengine:entity/poles","4":"modelengine:entity/magmasixteenx"},"elements":[{"name":"base","from":[6.3199997,10.879999,1.2199997],"to":[9.56,11.48,12.32],"rotation":{"angle":-22.5,"axis":"x","origin":[8.0,6.6799994,14.420001]},"faces":{"down":{"uv":[0.0,0.0,1.35,9.25],"rotation":0,"texture":"#1","tintindex":0},"east":{"uv":[0.0,0.0,4.625,0.5],"rotation":0,"texture":"#1","tintindex":0},"north":{"uv":[0.0,0.0,1.35,0.5],"rotation":0,"texture":"#1","tintindex":0},"south":{"uv":[0.0,0.0,1.35,0.5],"rotation":0,"texture":"#1","tintindex":0},"up":{"uv":[0.0,0.0,1.35,9.25],"rotation":0,"texture":"#1","tintindex":0},"west":{"uv":[0.0,0.0,4.625,0.5],"rotation":0,"texture":"#1","tintindex":0}}},{"name":"base","from":[6.74,11.179999,-0.46000051],"to":[9.2,12.860001,-0.10000038],"rotation":{"angle":-22.5,"axis":"x","origin":[8.0,6.6799994,14.420001]},"faces":{"down":{"uv":[0.0,0.0,1.025,0.3],"rotation":0,"texture":"#1","tintindex":0},"east":{"uv":[0.0,0.0,0.15,1.4],"rotation":0,"texture":"#1","tintindex":0},"north":{"uv":[0.0,0.0,1.025,1.4],"rotation":0,"texture":"#1","tintindex":0},"south":{"uv":[0.0,0.0,1.025,1.4],"rotation":0,"texture":"#1","tintindex":0},"up":{"uv":[0.0,0.0,1.025,0.3],"rotation":0,"texture":"#1","tintindex":0},"west":{"uv":[0.0,0.0,0.15,1.4],"rotation":0,"texture":"#1","tintindex":0}}},{"name":"base","from":[5.06,11.299999,4.3999996],"to":[10.82,12.860001,4.94],"rotation":{"angle":-22.5,"axis":"x","origin":[8.0,6.6799994,14.420001]},"faces":{"down":{"uv":[0.0,0.0,2.4,0.45],"rotation":0,"texture":"#1","tintindex":0},"east":{"uv":[0.0,0.0,0.225,1.3],"rotation":0,"texture":"#1","tintindex":0},"north":{"uv":[0.0,0.0,2.4,1.3],"rotation":0,"texture":"#1","tintindex":0},"south":{"uv":[0.0,0.0,2.4,1.3],"rotation":0,"texture":"#1","tintindex":0},"up":{"uv":[0.0,0.0,2.4,0.45],"rotation":0,"texture":"#1","tintindex":0},"west":{"uv":[0.0,0.0,0.225,1.3],"rotation":0,"texture":"#1","tintindex":0}}},{"name":"base","from":[2.8399997,11.299999,10.1],"to":[13.04,11.959999,13.94],"rotation":{"angle":-22.5,"axis":"x","origin":[8.0,6.6799994,14.420001]},"faces":{"down":{"uv":[0.0,0.0,4.25,3.2],"rotation":0,"texture":"#1","tintindex":0},"east":{"uv":[0.0,0.0,1.6,0.55],"rotation":0,"texture":"#1","tintindex":0},"north":{"uv":[0.0,0.0,4.25,0.55],"rotation":0,"texture":"#1","tintindex":0},"south":{"uv":[0.0,0.0,4.25,0.55],"rotation":0,"texture":"#1","tintindex":0},"up":{"uv":[0.0,0.0,4.25,3.2],"rotation":0,"texture":"#1","tintindex":0},"west":{"uv":[0.0,0.0,1.6,0.55],"rotation":0,"texture":"#1","tintindex":0}}},{"name":"base","from":[0.7999997,10.759999,11.18],"to":[15.08,11.9,12.14],"rotation":{"angle":-22.5,"axis":"x","origin":[8.0,6.6799994,14.420001]},"faces":{"down":{"uv":[0.0,0.0,5.95,0.8],"rotation":0,"texture":"#1","tintindex":0},"east":{"uv":[0.0,0.0,0.4,0.95],"rotation":0,"texture":"#1","tintindex":0},"north":{"uv":[0.0,0.0,5.95,0.95],"rotation":0,"texture":"#1","tintindex":0},"south":{"uv":[0.0,0.0,5.95,0.95],"rotation":0,"texture":"#1","tintindex":0},"up":{"uv":[0.0,0.0,5.95,0.8],"rotation":0,"texture":"#1","tintindex":0},"west":{"uv":[0.0,0.0,0.4,0.95],"rotation":0,"texture":"#1","tintindex":0}}},{"name":"base","from":[2.8399997,10.759999,12.02],"to":[13.04,17.18,12.860001],"rotation":{"angle":0.0,"axis":"x","origin":[8.0,6.6799994,14.420001]},"faces":{"down":{"uv":[0.0,0.0,4.25,0.7],"rotation":0,"texture":"#1","tintindex":0},"east":{"uv":[0.0,0.0,0.35,5.35],"rotation":0,"texture":"#1","tintindex":0},"north":{"uv":[0.0,0.0,4.25,2.675],"rotation":0,"texture":"#1","tintindex":0},"south":{"uv":[0.0,0.0,4.25,5.35],"rotation":0,"texture":"#1","tintindex":0},"up":{"uv":[0.0,0.0,4.25,0.7],"rotation":0,"texture":"#1","tintindex":0},"west":{"uv":[0.0,0.0,0.35,5.35],"rotation":0,"texture":"#1","tintindex":0}}},{"name":"base","from":[2.8399997,15.439999,8.18],"to":[4.7,17.420002,9.02],"rotation":{"angle":22.5,"axis":"x","origin":[8.0,6.6799994,14.420001]},"faces":{"down":{"uv":[0.0,0.0,0.775,0.7],"rotation":0,"texture":"#1","tintindex":0},"east":{"uv":[0.0,0.0,0.35,1.65],"rotation":0,"texture":"#1","tintindex":0},"north":{"uv":[0.0,0.0,0.775,1.65],"rotation":0,"texture":"#1","tintindex":0},"south":{"uv":[0.0,0.0,0.775,1.65],"rotation":0,"texture":"#1","tintindex":0},"up":{"uv":[0.0,0.0,0.775,0.7],"rotation":0,"texture":"#1","tintindex":0},"west":{"uv":[0.0,0.0,0.35,1.65],"rotation":0,"texture":"#1","tintindex":0}}},{"name":"base","from":[11.18,15.439999,8.18],"to":[13.04,17.420002,9.02],"rotation":{"angle":22.5,"axis":"x","origin":[8.0,6.6799994,14.420001]},"faces":{"down":{"uv":[0.0,0.0,0.775,0.7],"rotation":0,"texture":"#1","tintindex":0},"east":{"uv":[0.0,0.0,0.35,1.65],"rotation":0,"texture":"#1","tintindex":0},"north":{"uv":[0.0,0.0,0.775,1.65],"rotation":0,"texture":"#1","tintindex":0},"south":{"uv":[0.0,0.0,0.775,1.65],"rotation":0,"texture":"#1","tintindex":0},"up":{"uv":[0.0,0.0,0.775,0.7],"rotation":0,"texture":"#1","tintindex":0},"west":{"uv":[0.0,0.0,0.35,1.65],"rotation":0,"texture":"#1","tintindex":0}}},{"name":"base","from":[7.58,12.200001,5.54],"to":[8.24,29.54,6.38],"rotation":{"angle":45.0,"axis":"x","origin":[8.0,6.6799994,14.420001]},"faces":{"down":{"uv":[0.0,0.0,0.275,0.35],"rotation":0,"texture":"#1","tintindex":0},"east":{"uv":[0.0,0.0,0.35,7.225],"rotation":0,"texture":"#3","tintindex":0},"north":{"uv":[0.0,0.0,0.275,7.225],"rotation":0,"texture":"#3","tintindex":0},"south":{"uv":[0.0,0.0,0.275,7.225],"rotation":0,"texture":"#3","tintindex":0},"up":{"uv":[0.0,0.0,0.275,0.35],"rotation":0,"texture":"#3","tintindex":0},"west":{"uv":[0.0,0.0,0.35,7.225],"rotation":0,"texture":"#3","tintindex":0}}},{"name":"base","from":[4.7,15.439999,8.42],"to":[11.54,17.3,8.780001],"rotation":{"angle":22.5,"axis":"x","origin":[8.0,6.6799994,14.420001]},"faces":{"down":{"uv":[0.0,0.0,2.85,0.3],"rotation":0,"texture":"#1","tintindex":0},"east":{"uv":[0.0,0.0,0.15,1.55],"rotation":0,"texture":"#1","tintindex":0},"north":{"uv":[0.0,0.0,2.85,1.55],"rotation":0,"texture":"#1","tintindex":0},"south":{"uv":[0.0,0.0,2.85,1.55],"rotation":0,"texture":"#1","tintindex":0},"up":{"uv":[0.0,0.0,2.85,0.3],"rotation":0,"texture":"#1","tintindex":0},"west":{"uv":[0.0,0.0,0.15,1.55],"rotation":0,"texture":"#1","tintindex":0}}},{"name":"base","from":[2.8399997,11.299999,9.74],"to":[3.4999998,16.82,14.6],"rotation":{"angle":-22.5,"axis":"x","origin":[8.0,6.6799994,14.420001]},"faces":{"down":{"uv":[0.0,0.0,0.275,4.05],"rotation":0,"texture":"#1","tintindex":0},"east":{"uv":[0.0,0.0,2.025,4.6],"rotation":0,"texture":"#1","tintindex":0},"north":{"uv":[0.0,0.0,0.275,4.6],"rotation":0,"texture":"#1","tintindex":0},"south":{"uv":[0.0,0.0,0.275,4.6],"rotation":0,"texture":"#1","tintindex":0},"up":{"uv":[0.0,0.0,0.275,4.05],"rotation":0,"texture":"#1","tintindex":0},"west":{"uv":[0.0,0.0,2.025,4.6],"rotation":0,"texture":"#1","tintindex":0}}},{"name":"base","from":[2.8399997,13.279999,14.179999],"to":[3.4999998,16.82,15.440001],"rotation":{"angle":-22.5,"axis":"x","origin":[8.0,6.6799994,14.420001]},"faces":{"down":{"uv":[0.0,0.0,0.275,1.05],"rotation":0,"texture":"#1","tintindex":0},"east":{"uv":[0.0,0.0,0.525,2.95],"rotation":0,"texture":"#1","tintindex":0},"north":{"uv":[0.0,0.0,0.275,2.95],"rotation":0,"texture":"#1","tintindex":0},"south":{"uv":[0.0,0.0,0.275,2.95],"rotation":0,"texture":"#1","tintindex":0},"up":{"uv":[0.0,0.0,0.275,1.05],"rotation":0,"texture":"#1","tintindex":0},"west":{"uv":[0.0,0.0,0.525,2.95],"rotation":0,"texture":"#1","tintindex":0}}},{"name":"base","from":[12.38,15.259998,15.2],"to":[13.04,16.82,16.279999],"rotation":{"angle":-22.5,"axis":"x","origin":[8.0,6.6799994,14.420001]},"faces":{"down":{"uv":[0.0,0.0,0.275,0.9],"rotation":0,"texture":"#1","tintindex":0},"east":{"uv":[0.0,0.0,0.45,1.3],"rotation":0,"texture":"#1","tintindex":0},"north":{"uv":[0.0,0.0,0.275,1.3],"rotation":0,"texture":"#1","tintindex":0},"south":{"uv":[0.0,0.0,0.275,1.3],"rotation":0,"texture":"#1","tintindex":0},"up":{"uv":[0.0,0.0,0.275,0.9],"rotation":0,"texture":"#1","tintindex":0},"west":{"uv":[0.0,0.0,0.45,1.3],"rotation":0,"texture":"#1","tintindex":0}}},{"name":"base","from":[12.38,13.279999,14.179999],"to":[13.04,16.82,15.440001],"rotation":{"angle":-22.5,"axis":"x","origin":[8.0,6.6799994,14.420001]},"faces":{"down":{"uv":[0.0,0.0,0.275,1.05],"rotation":0,"texture":"#1","tintindex":0},"east":{"uv":[0.0,0.0,0.525,2.95],"rotation":0,"texture":"#1","tintindex":0},"north":{"uv":[0.0,0.0,0.275,2.95],"rotation":0,"texture":"#1","tintindex":0},"south":{"uv":[0.0,0.0,0.275,2.95],"rotation":0,"texture":"#1","tintindex":0},"up":{"uv":[0.0,0.0,0.275,1.05],"rotation":0,"texture":"#1","tintindex":0},"west":{"uv":[0.0,0.0,0.525,2.95],"rotation":0,"texture":"#1","tintindex":0}}},{"name":"base","from":[2.8399997,15.259998,15.2],"to":[3.4999998,16.82,16.279999],"rotation":{"angle":-22.5,"axis":"x","origin":[8.0,6.6799994,14.420001]},"faces":{"down":{"uv":[0.0,0.0,0.275,0.9],"rotation":0,"texture":"#1","tintindex":0},"east":{"uv":[0.0,0.0,0.45,1.3],"rotation":0,"texture":"#1","tintindex":0},"north":{"uv":[0.0,0.0,0.275,1.3],"rotation":0,"texture":"#1","tintindex":0},"south":{"uv":[0.0,0.0,0.275,1.3],"rotation":0,"texture":"#1","tintindex":0},"up":{"uv":[0.0,0.0,0.275,0.9],"rotation":0,"texture":"#1","tintindex":0},"west":{"uv":[0.0,0.0,0.45,1.3],"rotation":0,"texture":"#1","tintindex":0}}},{"name":"base","from":[12.38,11.299999,9.74],"to":[13.04,16.82,14.660001],"rotation":{"angle":-22.5,"axis":"x","origin":[8.0,6.6799994,14.420001]},"faces":{"down":{"uv":[0.0,0.0,0.275,4.1],"rotation":0,"texture":"#1","tintindex":0},"east":{"uv":[0.0,0.0,2.05,4.6],"rotation":0,"texture":"#1","tintindex":0},"north":{"uv":[0.0,0.0,0.275,4.6],"rotation":0,"texture":"#1","tintindex":0},"south":{"uv":[0.0,0.0,0.275,4.6],"rotation":0,"texture":"#1","tintindex":0},"up":{"uv":[0.0,0.0,0.275,4.1],"rotation":0,"texture":"#1","tintindex":0},"west":{"uv":[0.0,0.0,2.05,4.6],"rotation":0,"texture":"#1","tintindex":0}}},{"name":"base","from":[4.46,11.299999,6.8],"to":[11.18,11.959999,12.32],"rotation":{"angle":-22.5,"axis":"x","origin":[8.0,6.6799994,14.420001]},"faces":{"down":{"uv":[0.0,0.0,2.8,4.6],"rotation":0,"texture":"#1","tintindex":0},"east":{"uv":[0.0,0.0,2.3,0.55],"rotation":0,"texture":"#1","tintindex":0},"north":{"uv":[0.0,0.0,2.8,0.55],"rotation":0,"texture":"#1","tintindex":0},"south":{"uv":[0.0,0.0,2.8,0.55],"rotation":0,"texture":"#1","tintindex":0},"up":{"uv":[0.0,0.0,2.8,4.6],"rotation":0,"texture":"#1","tintindex":0},"west":{"uv":[0.0,0.0,2.3,0.55],"rotation":0,"texture":"#1","tintindex":0}}},{"name":"cube","from":[8.48,7.999999,2.8999999],"to":[9.08,32.0,3.4999998],"rotation":{"angle":-22.5,"axis":"z","origin":[8.0,3.7999992,8.0]},"faces":{"down":{"uv":[0.0,0.0,0.25,0.25],"rotation":0,"texture":"#3","tintindex":0},"east":{"uv":[0.0,0.0,0.25,10.0],"rotation":0,"texture":"#3","tintindex":0},"north":{"uv":[0.0,0.0,0.25,10.0],"rotation":0,"texture":"#3","tintindex":0},"south":{"uv":[0.0,0.0,0.25,10.0],"rotation":0,"texture":"#3","tintindex":0},"up":{"uv":[0.0,0.0,0.25,0.25],"rotation":0,"texture":"#3","tintindex":0},"west":{"uv":[0.0,0.0,0.25,10.0],"rotation":0,"texture":"#3","tintindex":0}}},{"name":"cube","from":[6.6800003,7.999999,2.8999999],"to":[7.28,32.0,3.4999998],"rotation":{"angle":22.5,"axis":"z","origin":[8.0,3.7999992,8.0]},"faces":{"down":{"uv":[0.0,0.0,0.25,0.25],"rotation":0,"texture":"#3","tintindex":0},"east":{"uv":[0.0,0.0,0.25,10.0],"rotation":0,"texture":"#3","tintindex":0},"north":{"uv":[0.0,0.0,0.25,10.0],"rotation":0,"texture":"#3","tintindex":0},"south":{"uv":[0.0,0.0,0.25,10.0],"rotation":0,"texture":"#3","tintindex":0},"up":{"uv":[0.0,0.0,0.25,0.25],"rotation":0,"texture":"#3","tintindex":0},"west":{"uv":[0.0,0.0,0.25,10.0],"rotation":0,"texture":"#3","tintindex":0}}}],"display":{"head":{"translation":[0.0,9.280003,0.0],"rotation":[0.0,0.0,0.0],"scale":[3.8095,3.8095,3.8095]}}}