{"textures":{"0":"modelengine:entity/frost_spider"},"elements":[{"name":"cube","from":[6.8,8.0,8.0],"to":[9.2,9.8,8.6],"rotation":{"angle":0.0,"axis":"x","origin":[8.0,8.0,8.0]},"faces":{"down":{"uv":[12.75,2.75,11.75,3.0],"rotation":0,"texture":"#0","tintindex":0},"east":{"uv":[7.0,12.25,7.25,13.0],"rotation":0,"texture":"#0","tintindex":0},"north":{"uv":[0.5,8.75,1.5,9.5],"rotation":0,"texture":"#0","tintindex":0},"south":{"uv":[9.0,3.75,10.0,4.5],"rotation":0,"texture":"#0","tintindex":0},"up":{"uv":[12.75,2.75,11.75,2.5],"rotation":0,"texture":"#0","tintindex":0},"west":{"uv":[13.25,2.75,13.5,3.5],"rotation":0,"texture":"#0","tintindex":0}}},{"name":"cube","from":[6.2,7.7,3.1999998],"to":[9.8,10.1,8.0],"rotation":{"angle":0.0,"axis":"x","origin":[8.0,7.7,8.0]},"faces":{"down":{"uv":[8.5,2.0,7.0,4.0],"rotation":0,"texture":"#0","tintindex":0},"east":{"uv":[7.0,4.0,9.0,5.0],"rotation":0,"texture":"#0","tintindex":0},"north":{"uv":[7.0,6.0,8.5,7.0],"rotation":0,"texture":"#0","tintindex":0},"south":{"uv":[8.5,0.0,10.0,1.0],"rotation":0,"texture":"#0","tintindex":0},"up":{"uv":[8.5,2.0,7.0,0.0],"rotation":0,"texture":"#0","tintindex":0},"west":{"uv":[7.0,5.0,9.0,6.0],"rotation":0,"texture":"#0","tintindex":0}}},{"name":"cube","from":[8.3,9.35,2.8999999],"to":[9.2,10.25,3.4999998],"rotation":{"angle":0.0,"axis":"x","origin":[8.0,8.15,7.7]},"faces":{"down":{"uv":[10.5,10.75,10.0,11.0],"rotation":0,"texture":"#0","tintindex":0},"east":{"uv":[13.25,5.5,13.5,6.0],"rotation":0,"texture":"#0","tintindex":0},"north":{"uv":[13.25,0.0,13.75,0.5],"rotation":0,"texture":"#0","tintindex":0},"south":{"uv":[13.25,0.5,13.75,1.0],"rotation":0,"texture":"#0","tintindex":0},"up":{"uv":[5.0,7.5,4.5,7.25],"rotation":0,"texture":"#0","tintindex":0},"west":{"uv":[13.25,6.0,13.5,6.5],"rotation":0,"texture":"#0","tintindex":0}}},{"name":"cube","from":[6.8,9.35,2.8999999],"to":[7.7,10.25,3.4999998],"rotation":{"angle":0.0,"axis":"x","origin":[8.0,8.15,7.7]},"faces":{"down":{"uv":[12.25,11.5,11.75,11.75],"rotation":0,"texture":"#0","tintindex":0},"east":{"uv":[13.25,6.5,13.5,7.0],"rotation":0,"texture":"#0","tintindex":0},"north":{"uv":[13.25,1.0,13.75,1.5],"rotation":0,"texture":"#0","tintindex":0},"south":{"uv":[13.25,2.25,13.75,2.75],"rotation":0,"texture":"#0","tintindex":0},"up":{"uv":[11.25,3.75,10.75,3.5],"rotation":0,"texture":"#0","tintindex":0},"west":{"uv":[13.25,7.0,13.5,7.5],"rotation":0,"texture":"#0","tintindex":0}}},{"name":"cube","from":[9.35,9.05,3.0499997],"to":[9.950001,9.65,3.6499999],"rotation":{"angle":0.0,"axis":"x","origin":[8.75,7.85,7.85]},"faces":{"down":{"uv":[13.5,7.75,13.25,8.0],"rotation":0,"texture":"#0","tintindex":0},"east":{"uv":[13.0,4.5,13.25,4.75],"rotation":0,"texture":"#0","tintindex":0},"north":{"uv":[13.0,2.25,13.25,2.5],"rotation":0,"texture":"#0","tintindex":0},"south":{"uv":[13.0,12.75,13.25,13.0],"rotation":0,"texture":"#0","tintindex":0},"up":{"uv":[13.5,7.75,13.25,7.5],"rotation":0,"texture":"#0","tintindex":0},"west":{"uv":[13.25,1.5,13.5,1.75],"rotation":0,"texture":"#0","tintindex":0}}},{"name":"cube","from":[6.05,9.05,3.0499997],"to":[6.6499996,9.65,3.6499999],"rotation":{"angle":0.0,"axis":"x","origin":[7.25,7.85,7.85]},"faces":{"down":{"uv":[7.5,13.5,7.25,13.75],"rotation":0,"texture":"#0","tintindex":0},"east":{"uv":[1.25,13.5,1.5,13.75],"rotation":0,"texture":"#0","tintindex":0},"north":{"uv":[1.0,13.5,1.25,13.75],"rotation":0,"texture":"#0","tintindex":0},"south":{"uv":[1.5,13.5,1.75,13.75],"rotation":0,"texture":"#0","tintindex":0},"up":{"uv":[7.25,13.75,7.0,13.5],"rotation":0,"texture":"#0","tintindex":0},"west":{"uv":[1.75,13.5,2.0,13.75],"rotation":0,"texture":"#0","tintindex":0}}},{"name":"cube","from":[8.15,8.9,3.0499997],"to":[8.45,9.2,3.6499999],"rotation":{"angle":0.0,"axis":"x","origin":[7.25,7.7,7.85]},"faces":{"down":{"uv":[1.0,13.5,0.75,13.75],"rotation":0,"texture":"#0","tintindex":0},"east":{"uv":[13.25,12.75,13.5,13.0],"rotation":0,"texture":"#0","tintindex":0},"north":{"uv":[13.25,10.5,13.5,10.75],"rotation":0,"texture":"#0","tintindex":0},"south":{"uv":[0.0,13.5,0.25,13.75],"rotation":0,"texture":"#0","tintindex":0},"up":{"uv":[0.75,13.75,0.5,13.5],"rotation":0,"texture":"#0","tintindex":0},"west":{"uv":[0.25,13.5,0.5,13.75],"rotation":0,"texture":"#0","tintindex":0}}},{"name":"cube","from":[7.55,8.9,3.0499997],"to":[7.85,9.2,3.6499999],"rotation":{"angle":0.0,"axis":"x","origin":[8.75,7.7,7.85]},"faces":{"down":{"uv":[10.5,13.5,10.25,13.75],"rotation":0,"texture":"#0","tintindex":0},"east":{"uv":[9.25,13.5,9.5,13.75],"rotation":0,"texture":"#0","tintindex":0},"north":{"uv":[9.0,13.5,9.25,13.75],"rotation":0,"texture":"#0","tintindex":0},"south":{"uv":[9.5,13.5,9.75,13.75],"rotation":0,"texture":"#0","tintindex":0},"up":{"uv":[10.25,13.75,10.0,13.5],"rotation":0,"texture":"#0","tintindex":0},"west":{"uv":[9.75,13.5,10.0,13.75],"rotation":0,"texture":"#0","tintindex":0}}},{"name":"cube","from":[9.35,9.65,3.7999997],"to":[9.950001,10.25,4.3999996],"rotation":{"angle":0.0,"axis":"x","origin":[8.75,8.45,8.6]},"faces":{"down":{"uv":[13.5,10.25,13.25,10.5],"rotation":0,"texture":"#0","tintindex":0},"east":{"uv":[13.25,8.25,13.5,8.5],"rotation":0,"texture":"#0","tintindex":0},"north":{"uv":[13.25,8.0,13.5,8.25],"rotation":0,"texture":"#0","tintindex":0},"south":{"uv":[13.25,8.5,13.5,8.75],"rotation":0,"texture":"#0","tintindex":0},"up":{"uv":[13.5,10.25,13.25,10.0],"rotation":0,"texture":"#0","tintindex":0},"west":{"uv":[13.25,9.75,13.5,10.0],"rotation":0,"texture":"#0","tintindex":0}}},{"name":"cube","from":[6.05,9.65,3.7999997],"to":[6.6499996,10.25,4.3999996],"rotation":{"angle":0.0,"axis":"x","origin":[7.25,8.45,8.6]},"faces":{"down":{"uv":[9.0,13.5,8.75,13.75],"rotation":0,"texture":"#0","tintindex":0},"east":{"uv":[7.75,13.5,8.0,13.75],"rotation":0,"texture":"#0","tintindex":0},"north":{"uv":[7.5,13.5,7.75,13.75],"rotation":0,"texture":"#0","tintindex":0},"south":{"uv":[8.0,13.5,8.25,13.75],"rotation":0,"texture":"#0","tintindex":0},"up":{"uv":[8.75,13.75,8.5,13.5],"rotation":0,"texture":"#0","tintindex":0},"west":{"uv":[8.25,13.5,8.5,13.75],"rotation":0,"texture":"#0","tintindex":0}}}],"display":{"head":{"translation":[0.0,-6.4,0.0],"rotation":[0.0,0.0,0.0],"scale":[3.8095,3.8095,3.8095]}}}