{"textures":{"0":"modelengine:entity/firedragon"},"elements":[{"name":"cube","from":[7.143321,7.0431457,-7.296422],"to":[8.805496,21.171635,-5.634247],"rotation":{"angle":45.0,"axis":"x","origin":[7.9744086,7.743428,-6.0410705]},"faces":{"down":{"uv":[3.75,8.6875,3.5625,8.5],"rotation":0,"texture":"#0","tintindex":0},"east":{"uv":[0.9375,5.6875,0.75,7.3125],"rotation":0,"texture":"#0","tintindex":0},"north":{"uv":[1.125,5.6875,0.9375,7.3125],"rotation":0,"texture":"#0","tintindex":0},"south":{"uv":[0.75,5.6875,0.5625,7.3125],"rotation":0,"texture":"#0","tintindex":0},"up":{"uv":[7.3125,8.375,7.125,8.5625],"rotation":0,"texture":"#0","tintindex":0},"west":{"uv":[1.3125,5.6875,1.125,7.3125],"rotation":0,"texture":"#0","tintindex":0}}},{"name":"cube","from":[7.143321,16.869083,2.0808563],"to":[8.805496,25.179958,3.7430305],"rotation":{"angle":0.0,"axis":"x","origin":[21.271805,-3.9080997,3.7430305]},"faces":{"down":{"uv":[7.25,9.3125,7.0625,9.125],"rotation":0,"texture":"#0","tintindex":0},"east":{"uv":[3.75,7.5625,3.5625,8.5],"rotation":0,"texture":"#0","tintindex":0},"north":{"uv":[0.8125,7.75,0.625,8.6875],"rotation":0,"texture":"#0","tintindex":0},"south":{"uv":[0.8125,4.375,0.625,5.3125],"rotation":0,"texture":"#0","tintindex":0},"up":{"uv":[9.25,7.75,9.0625,7.9375],"rotation":0,"texture":"#0","tintindex":0},"west":{"uv":[1.0,7.75,0.8125,8.6875],"rotation":0,"texture":"#0","tintindex":0}}},{"name":"cube","from":[7.143321,25.179958,0.41868114],"to":[8.805496,26.842136,10.391731],"rotation":{"angle":0.0,"axis":"x","origin":[21.271805,-8.063537,2.9119415]},"faces":{"down":{"uv":[0.1875,8.5,0.0,7.375],"rotation":0,"texture":"#0","tintindex":0},"east":{"uv":[8.3125,2.5,7.1875,2.6875],"rotation":0,"texture":"#0","tintindex":0},"north":{"uv":[9.3125,1.875,9.125,2.0625],"rotation":0,"texture":"#0","tintindex":0},"south":{"uv":[7.4375,9.125,7.25,9.3125],"rotation":0,"texture":"#0","tintindex":0},"up":{"uv":[1.3125,7.3125,1.125,8.4375],"rotation":0,"texture":"#0","tintindex":0},"west":{"uv":[8.3125,3.625,7.1875,3.8125],"rotation":0,"texture":"#0","tintindex":0}}},{"name":"cube","from":[7.697379,25.734016,-1.7975521],"to":[8.251438,26.288074,0.41868114],"rotation":{"angle":0.0,"axis":"x","origin":[21.271805,-8.063537,-8.169222]},"faces":{"down":{"uv":[4.625,9.625,4.5625,9.375],"rotation":0,"texture":"#0","tintindex":0},"east":{"uv":[9.625,0.0,9.375,0.0625],"rotation":0,"texture":"#0","tintindex":0},"north":{"uv":[9.5,9.1875,9.4375,9.25],"rotation":0,"texture":"#0","tintindex":0},"south":{"uv":[9.5,9.0,9.4375,9.0625],"rotation":0,"texture":"#0","tintindex":0},"up":{"uv":[0.1875,9.375,0.125,9.625],"rotation":0,"texture":"#0","tintindex":0},"west":{"uv":[9.625,0.0625,9.375,0.125],"rotation":0,"texture":"#0","tintindex":0}}},{"name":"cube","from":[7.143321,26.842136,8.729557],"to":[8.805496,28.50431,17.040428],"rotation":{"angle":0.0,"axis":"x","origin":[21.271805,-6.4013624,9.560642]},"faces":{"down":{"uv":[3.1875,8.6875,3.0,7.75],"rotation":0,"texture":"#0","tintindex":0},"east":{"uv":[1.875,0.75,0.9375,0.9375],"rotation":0,"texture":"#0","tintindex":0},"north":{"uv":[9.3125,6.4375,9.125,6.625],"rotation":0,"texture":"#0","tintindex":0},"south":{"uv":[9.3125,5.75,9.125,5.9375],"rotation":0,"texture":"#0","tintindex":0},"up":{"uv":[3.0,7.75,2.8125,8.6875],"rotation":0,"texture":"#0","tintindex":0},"west":{"uv":[2.8125,7.75,1.875,7.9375],"rotation":0,"texture":"#0","tintindex":0}}},{"name":"cube","from":[7.143321,28.50431,15.378254],"to":[8.805496,30.166485,22.85804],"rotation":{"angle":0.0,"axis":"x","origin":[21.271805,-4.739187,16.209343]},"faces":{"down":{"uv":[2.6875,8.8125,2.5,7.9375],"rotation":0,"texture":"#0","tintindex":0},"east":{"uv":[8.6875,7.4375,7.8125,7.625],"rotation":0,"texture":"#0","tintindex":0},"north":{"uv":[9.3125,6.8125,9.125,7.0],"rotation":0,"texture":"#0","tintindex":0},"south":{"uv":[9.3125,6.625,9.125,6.8125],"rotation":0,"texture":"#0","tintindex":0},"up":{"uv":[2.5,7.9375,2.3125,8.8125],"rotation":0,"texture":"#0","tintindex":0},"west":{"uv":[6.3125,7.9375,5.4375,8.125],"rotation":0,"texture":"#0","tintindex":0}}},{"name":"cube","from":[7.143321,30.166485,21.195866],"to":[8.805496,30.99757,32.0],"rotation":{"angle":0.0,"axis":"x","origin":[21.271805,-3.9080997,16.176292]},"faces":{"down":{"uv":[6.5625,8.1875,6.375,6.9375],"rotation":0,"texture":"#0","tintindex":0},"east":{"uv":[9.25,4.875,8.0,5.0],"rotation":0,"texture":"#0","tintindex":0},"north":{"uv":[8.375,9.25,8.1875,9.375],"rotation":0,"texture":"#0","tintindex":0},"south":{"uv":[2.0625,9.25,1.875,9.375],"rotation":0,"texture":"#0","tintindex":0},"up":{"uv":[3.75,6.3125,3.5625,7.5625],"rotation":0,"texture":"#0","tintindex":0},"west":{"uv":[9.25,5.0,8.0,5.125],"rotation":0,"texture":"#0","tintindex":0}}},{"name":"cube","from":[7.9744086,29.335396,21.195866],"to":[7.9744086,30.99757,31.168919],"rotation":{"angle":0.0,"axis":"x","origin":[20.44072,-3.9080997,22.026955]},"faces":{"down":{"uv":[0.0,1.125,0.0,0.0],"rotation":0,"texture":"#0","tintindex":0},"east":{"uv":[8.4375,7.0625,7.3125,7.25],"rotation":0,"texture":"#0","tintindex":0},"north":{"uv":[0.0,0.0,0.0,0.1875],"rotation":0,"texture":"#0","tintindex":0},"south":{"uv":[0.0,0.0,0.0,0.1875],"rotation":0,"texture":"#0","tintindex":0},"up":{"uv":[0.0,0.0,0.0,1.125],"rotation":0,"texture":"#0","tintindex":0},"west":{"uv":[8.5625,6.125,7.4375,6.3125],"rotation":0,"texture":"#0","tintindex":0}}},{"name":"cube","from":[7.9744086,28.50431,20.364777],"to":[7.9744086,30.166485,30.33783],"rotation":{"angle":0.0,"axis":"x","origin":[20.44072,-4.739187,21.195866]},"faces":{"down":{"uv":[0.0,1.125,0.0,0.0],"rotation":0,"texture":"#0","tintindex":0},"east":{"uv":[8.5625,6.3125,7.4375,6.5],"rotation":0,"texture":"#0","tintindex":0},"north":{"uv":[0.0,0.0,0.0,0.1875],"rotation":0,"texture":"#0","tintindex":0},"south":{"uv":[0.0,0.0,0.0,0.1875],"rotation":0,"texture":"#0","tintindex":0},"up":{"uv":[0.0,0.0,0.0,1.125],"rotation":0,"texture":"#0","tintindex":0},"west":{"uv":[8.625,0.1875,7.5,0.375],"rotation":0,"texture":"#0","tintindex":0}}},{"name":"cube","from":[7.9744086,27.673222,17.040428],"to":[7.9744086,29.335396,28.675652],"rotation":{"angle":0.0,"axis":"x","origin":[20.44072,-5.5702753,20.364777]},"faces":{"down":{"uv":[0.0,1.3125,0.0,0.0],"rotation":0,"texture":"#0","tintindex":0},"east":{"uv":[7.9375,1.625,6.625,1.8125],"rotation":0,"texture":"#0","tintindex":0},"north":{"uv":[0.0,0.0,0.0,0.1875],"rotation":0,"texture":"#0","tintindex":0},"south":{"uv":[0.0,0.0,0.0,0.1875],"rotation":0,"texture":"#0","tintindex":0},"up":{"uv":[0.0,0.0,0.0,1.3125],"rotation":0,"texture":"#0","tintindex":0},"west":{"uv":[7.9375,5.3125,6.625,5.5],"rotation":0,"texture":"#0","tintindex":0}}},{"name":"cube","from":[7.9744086,26.842136,15.378254],"to":[7.9744086,27.673222,27.013481],"rotation":{"angle":0.0,"axis":"x","origin":[20.44072,-6.4013624,18.702602]},"faces":{"down":{"uv":[0.0,1.3125,0.0,0.0],"rotation":0,"texture":"#0","tintindex":0},"east":{"uv":[1.875,5.3125,0.5625,5.4375],"rotation":0,"texture":"#0","tintindex":0},"north":{"uv":[0.0,0.0,0.0,0.125],"rotation":0,"texture":"#0","tintindex":0},"south":{"uv":[0.0,0.0,0.0,0.125],"rotation":0,"texture":"#0","tintindex":0},"up":{"uv":[0.0,0.0,0.0,1.3125],"rotation":0,"texture":"#0","tintindex":0},"west":{"uv":[9.125,7.625,7.8125,7.75],"rotation":0,"texture":"#0","tintindex":0}}},{"name":"cube","from":[7.9744086,26.011047,10.391731],"to":[7.9744086,26.842136,25.351303],"rotation":{"angle":0.0,"axis":"x","origin":[20.44072,-7.2324495,17.040428]},"faces":{"down":{"uv":[0.0,1.6875,0.0,0.0],"rotation":0,"texture":"#0","tintindex":0},"east":{"uv":[9.125,6.5,7.4375,6.625],"rotation":0,"texture":"#0","tintindex":0},"north":{"uv":[0.0,0.0,0.0,0.125],"rotation":0,"texture":"#0","tintindex":0},"south":{"uv":[0.0,0.0,0.0,0.125],"rotation":0,"texture":"#0","tintindex":0},"up":{"uv":[0.0,0.0,0.0,1.6875],"rotation":0,"texture":"#0","tintindex":0},"west":{"uv":[9.1875,0.375,7.5,0.5],"rotation":0,"texture":"#0","tintindex":0}}},{"name":"cube","from":[7.9744086,24.348873,3.7430305],"to":[7.9744086,26.011047,24.520218],"rotation":{"angle":0.0,"axis":"x","origin":[20.44072,-8.063537,16.209343]},"faces":{"down":{"uv":[0.0,2.375,0.0,0.0],"rotation":0,"texture":"#0","tintindex":0},"east":{"uv":[6.5,0.375,4.125,0.5625],"rotation":0,"texture":"#0","tintindex":0},"north":{"uv":[0.0,0.0,0.0,0.1875],"rotation":0,"texture":"#0","tintindex":0},"south":{"uv":[0.0,0.0,0.0,0.1875],"rotation":0,"texture":"#0","tintindex":0},"up":{"uv":[0.0,0.0,0.0,2.375],"rotation":0,"texture":"#0","tintindex":0},"west":{"uv":[6.5,0.5625,4.125,0.75],"rotation":0,"texture":"#0","tintindex":0}}},{"name":"cube","from":[7.9744086,22.686699,3.7430305],"to":[7.9744086,24.348873,23.689129],"rotation":{"angle":0.0,"axis":"x","origin":[20.44072,-8.894625,16.209343]},"faces":{"down":{"uv":[0.0,2.25,0.0,0.0],"rotation":0,"texture":"#0","tintindex":0},"east":{"uv":[6.375,1.125,4.125,1.3125],"rotation":0,"texture":"#0","tintindex":0},"north":{"uv":[0.0,0.0,0.0,0.1875],"rotation":0,"texture":"#0","tintindex":0},"south":{"uv":[0.0,0.0,0.0,0.1875],"rotation":0,"texture":"#0","tintindex":0},"up":{"uv":[0.0,0.0,0.0,2.25],"rotation":0,"texture":"#0","tintindex":0},"west":{"uv":[6.375,1.3125,4.125,1.5],"rotation":0,"texture":"#0","tintindex":0}}},{"name":"cube","from":[7.9744086,20.193436,3.7430305],"to":[7.9744086,21.02452,27.013481],"rotation":{"angle":0.0,"axis":"x","origin":[20.44072,-14.712235,16.209343]},"faces":{"down":{"uv":[0.0,2.625,0.0,0.0],"rotation":0,"texture":"#0","tintindex":0},"east":{"uv":[8.125,4.0,5.5,4.125],"rotation":0,"texture":"#0","tintindex":0},"north":{"uv":[0.0,0.0,0.0,0.125],"rotation":0,"texture":"#0","tintindex":0},"south":{"uv":[0.0,0.0,0.0,0.125],"rotation":0,"texture":"#0","tintindex":0},"up":{"uv":[0.0,0.0,0.0,2.625],"rotation":0,"texture":"#0","tintindex":0},"west":{"uv":[8.125,4.125,5.5,4.25],"rotation":0,"texture":"#0","tintindex":0}}},{"name":"cube","from":[7.9744086,21.02452,3.7430305],"to":[7.9744086,21.85561,25.351303],"rotation":{"angle":0.0,"axis":"x","origin":[20.44072,-13.88115,16.209343]},"faces":{"down":{"uv":[0.0,2.4375,0.0,0.0],"rotation":0,"texture":"#0","tintindex":0},"east":{"uv":[8.0,2.125,5.5625,2.25],"rotation":0,"texture":"#0","tintindex":0},"north":{"uv":[0.0,0.0,0.0,0.125],"rotation":0,"texture":"#0","tintindex":0},"south":{"uv":[0.0,0.0,0.0,0.125],"rotation":0,"texture":"#0","tintindex":0},"up":{"uv":[0.0,0.0,0.0,2.4375],"rotation":0,"texture":"#0","tintindex":0},"west":{"uv":[8.0,2.25,5.5625,2.375],"rotation":0,"texture":"#0","tintindex":0}}},{"name":"cube","from":[7.9744086,21.85561,3.7430305],"to":[7.9744086,22.686699,24.520218],"rotation":{"angle":0.0,"axis":"x","origin":[20.44072,-13.050061,16.209343]},"faces":{"down":{"uv":[0.0,2.375,0.0,0.0],"rotation":0,"texture":"#0","tintindex":0},"east":{"uv":[3.6875,6.1875,1.3125,6.3125],"rotation":0,"texture":"#0","tintindex":0},"north":{"uv":[0.0,0.0,0.0,0.125],"rotation":0,"texture":"#0","tintindex":0},"south":{"uv":[0.0,0.0,0.0,0.125],"rotation":0,"texture":"#0","tintindex":0},"up":{"uv":[0.0,0.0,0.0,2.375],"rotation":0,"texture":"#0","tintindex":0},"west":{"uv":[6.875,6.1875,4.5,6.3125],"rotation":0,"texture":"#0","tintindex":0}}},{"name":"cube","from":[7.9744086,8.55821,5.405205],"to":[7.9744086,9.389299,13.71608],"rotation":{"angle":0.0,"axis":"x","origin":[20.44072,1.424692,11.222816]},"faces":{"down":{"uv":[0.0,0.9375,0.0,0.0],"rotation":0,"texture":"#0","tintindex":0},"east":{"uv":[9.0625,4.375,8.125,4.5],"rotation":0,"texture":"#0","tintindex":0},"north":{"uv":[0.0,0.0,0.0,0.125],"rotation":0,"texture":"#0","tintindex":0},"south":{"uv":[0.0,0.0,0.0,0.125],"rotation":0,"texture":"#0","tintindex":0},"up":{"uv":[0.0,0.0,0.0,0.9375],"rotation":0,"texture":"#0","tintindex":0},"west":{"uv":[9.125,0.0,8.1875,0.125],"rotation":0,"texture":"#0","tintindex":0}}},{"name":"cube","from":[7.9744086,9.389299,3.7430305],"to":[7.9744086,10.2203865,15.378254],"rotation":{"angle":0.0,"axis":"x","origin":[20.44072,0.52224994,11.222816]},"faces":{"down":{"uv":[0.0,1.3125,0.0,0.0],"rotation":0,"texture":"#0","tintindex":0},"east":{"uv":[8.625,7.9375,7.3125,8.0625],"rotation":0,"texture":"#0","tintindex":0},"north":{"uv":[0.0,0.0,0.0,0.125],"rotation":0,"texture":"#0","tintindex":0},"south":{"uv":[0.0,0.0,0.0,0.125],"rotation":0,"texture":"#0","tintindex":0},"up":{"uv":[0.0,0.0,0.0,1.3125],"rotation":0,"texture":"#0","tintindex":0},"west":{"uv":[9.25,1.625,7.9375,1.75],"rotation":0,"texture":"#0","tintindex":0}}},{"name":"cube","from":[7.9744086,10.2203865,2.9119415],"to":[7.9744086,11.051474,16.209343],"rotation":{"angle":0.0,"axis":"x","origin":[20.44072,0.05319023,11.222816]},"faces":{"down":{"uv":[0.0,1.5,0.0,0.0],"rotation":0,"texture":"#0","tintindex":0},"east":{"uv":[9.1875,3.1875,7.6875,3.3125],"rotation":0,"texture":"#0","tintindex":0},"north":{"uv":[0.0,0.0,0.0,0.125],"rotation":0,"texture":"#0","tintindex":0},"south":{"uv":[0.0,0.0,0.0,0.125],"rotation":0,"texture":"#0","tintindex":0},"up":{"uv":[0.0,0.0,0.0,1.5],"rotation":0,"texture":"#0","tintindex":0},"west":{"uv":[9.1875,3.3125,7.6875,3.4375],"rotation":0,"texture":"#0","tintindex":0}}},{"name":"cube","from":[7.9744086,11.882561,-2.0745811],"to":[7.9744086,12.713648,19.533691],"rotation":{"angle":0.0,"axis":"x","origin":[20.44072,0.8485999,12.8849945]},"faces":{"down":{"uv":[0.0,2.4375,0.0,0.0],"rotation":0,"texture":"#0","tintindex":0},"east":{"uv":[6.1875,5.6875,3.75,5.8125],"rotation":0,"texture":"#0","tintindex":0},"north":{"uv":[0.0,0.0,0.0,0.125],"rotation":0,"texture":"#0","tintindex":0},"south":{"uv":[0.0,0.0,0.0,0.125],"rotation":0,"texture":"#0","tintindex":0},"up":{"uv":[0.0,0.0,0.0,2.4375],"rotation":0,"texture":"#0","tintindex":0},"west":{"uv":[3.75,5.8125,1.3125,5.9375],"rotation":0,"texture":"#0","tintindex":0}}},{"name":"cube","from":[7.9744086,12.713648,-0.41240597],"to":[7.9744086,13.544736,21.195866],"rotation":{"angle":0.0,"axis":"x","origin":[20.44072,0.16284871,14.547169]},"faces":{"down":{"uv":[0.0,2.4375,0.0,0.0],"rotation":0,"texture":"#0","tintindex":0},"east":{"uv":[8.0,2.375,5.5625,2.5],"rotation":0,"texture":"#0","tintindex":0},"north":{"uv":[0.0,0.0,0.0,0.125],"rotation":0,"texture":"#0","tintindex":0},"south":{"uv":[0.0,0.0,0.0,0.125],"rotation":0,"texture":"#0","tintindex":0},"up":{"uv":[0.0,0.0,0.0,2.4375],"rotation":0,"texture":"#0","tintindex":0},"west":{"uv":[3.75,5.6875,1.3125,5.8125],"rotation":0,"texture":"#0","tintindex":0}}},{"name":"cube","from":[7.9744086,14.375823,1.2497683],"to":[7.9744086,15.20691,26.182392],"rotation":{"angle":0.0,"axis":"x","origin":[20.44072,-2.0754175,16.209343]},"faces":{"down":{"uv":[0.0,2.8125,0.0,0.0],"rotation":0,"texture":"#0","tintindex":0},"east":{"uv":[8.0,4.625,5.1875,4.75],"rotation":0,"texture":"#0","tintindex":0},"north":{"uv":[0.0,0.0,0.0,0.125],"rotation":0,"texture":"#0","tintindex":0},"south":{"uv":[0.0,0.0,0.0,0.125],"rotation":0,"texture":"#0","tintindex":0},"up":{"uv":[0.0,0.0,0.0,2.8125],"rotation":0,"texture":"#0","tintindex":0},"west":{"uv":[8.0,4.75,5.1875,4.875],"rotation":0,"texture":"#0","tintindex":0}}},{"name":"cube","from":[7.9744086,15.20691,2.0808563],"to":[7.9744086,16.037998,27.013481],"rotation":{"angle":0.0,"axis":"x","origin":[20.44072,-18.036587,16.209343]},"faces":{"down":{"uv":[0.0,2.8125,0.0,0.0],"rotation":0,"texture":"#0","tintindex":0},"east":{"uv":[7.6875,4.5,4.875,4.625],"rotation":0,"texture":"#0","tintindex":0},"north":{"uv":[0.0,0.0,0.0,0.125],"rotation":0,"texture":"#0","tintindex":0},"south":{"uv":[0.0,0.0,0.0,0.125],"rotation":0,"texture":"#0","tintindex":0},"up":{"uv":[0.0,0.0,0.0,2.8125],"rotation":0,"texture":"#0","tintindex":0},"west":{"uv":[8.0,5.1875,5.1875,5.3125],"rotation":0,"texture":"#0","tintindex":0}}},{"name":"cube","from":[7.9744086,18.531261,3.7430305],"to":[7.9744086,20.193436,27.844566],"rotation":{"angle":0.0,"axis":"x","origin":[20.44072,-15.543323,16.209343]},"faces":{"down":{"uv":[0.0,2.75,0.0,0.0],"rotation":0,"texture":"#0","tintindex":0},"east":{"uv":[6.6875,3.5,3.9375,3.6875],"rotation":0,"texture":"#0","tintindex":0},"north":{"uv":[0.0,0.0,0.0,0.1875],"rotation":0,"texture":"#0","tintindex":0},"south":{"uv":[0.0,0.0,0.0,0.1875],"rotation":0,"texture":"#0","tintindex":0},"up":{"uv":[0.0,0.0,0.0,2.75],"rotation":0,"texture":"#0","tintindex":0},"west":{"uv":[6.6875,3.6875,3.9375,3.875],"rotation":0,"texture":"#0","tintindex":0}}},{"name":"cube","from":[7.9744086,16.037998,2.9119415],"to":[7.9744086,17.700172,27.844566],"rotation":{"angle":0.0,"axis":"x","origin":[20.44072,-17.205498,16.209343]},"faces":{"down":{"uv":[0.0,2.8125,0.0,0.0],"rotation":0,"texture":"#0","tintindex":0},"east":{"uv":[6.1875,2.9375,3.375,3.125],"rotation":0,"texture":"#0","tintindex":0},"north":{"uv":[0.0,0.0,0.0,0.1875],"rotation":0,"texture":"#0","tintindex":0},"south":{"uv":[0.0,0.0,0.0,0.1875],"rotation":0,"texture":"#0","tintindex":0},"up":{"uv":[0.0,0.0,0.0,2.8125],"rotation":0,"texture":"#0","tintindex":0},"west":{"uv":[6.1875,3.125,3.375,3.3125],"rotation":0,"texture":"#0","tintindex":0}}},{"name":"cube","from":[7.9744086,17.700172,3.7430305],"to":[7.9744086,18.531261,28.675652],"rotation":{"angle":0.0,"axis":"x","origin":[20.44072,-16.374409,16.209343]},"faces":{"down":{"uv":[0.0,2.8125,0.0,0.0],"rotation":0,"texture":"#0","tintindex":0},"east":{"uv":[7.1875,2.5,4.375,2.625],"rotation":0,"texture":"#0","tintindex":0},"north":{"uv":[0.0,0.0,0.0,0.125],"rotation":0,"texture":"#0","tintindex":0},"south":{"uv":[0.0,0.0,0.0,0.125],"rotation":0,"texture":"#0","tintindex":0},"up":{"uv":[0.0,0.0,0.0,2.8125],"rotation":0,"texture":"#0","tintindex":0},"west":{"uv":[7.1875,2.625,4.375,2.75],"rotation":0,"texture":"#0","tintindex":0}}},{"name":"cube","from":[7.9744086,13.544736,0.41868114],"to":[7.9744086,14.375823,23.689129],"rotation":{"angle":0.0,"axis":"x","origin":[20.44072,-1.8230491,15.378254]},"faces":{"down":{"uv":[0.0,2.625,0.0,0.0],"rotation":0,"texture":"#0","tintindex":0},"east":{"uv":[8.125,4.25,5.5,4.375],"rotation":0,"texture":"#0","tintindex":0},"north":{"uv":[0.0,0.0,0.0,0.125],"rotation":0,"texture":"#0","tintindex":0},"south":{"uv":[0.0,0.0,0.0,0.125],"rotation":0,"texture":"#0","tintindex":0},"up":{"uv":[0.0,0.0,0.0,2.625],"rotation":0,"texture":"#0","tintindex":0},"west":{"uv":[8.125,4.375,5.5,4.5],"rotation":0,"texture":"#0","tintindex":0}}},{"name":"cube","from":[7.9744086,11.051474,1.2497683],"to":[7.9744086,11.882561,17.040428],"rotation":{"angle":0.0,"axis":"x","origin":[20.44072,2.1844249,11.222816]},"faces":{"down":{"uv":[0.0,1.8125,0.0,0.0],"rotation":0,"texture":"#0","tintindex":0},"east":{"uv":[8.75,0.625,6.9375,0.75],"rotation":0,"texture":"#0","tintindex":0},"north":{"uv":[0.0,0.0,0.0,0.125],"rotation":0,"texture":"#0","tintindex":0},"south":{"uv":[0.0,0.0,0.0,0.125],"rotation":0,"texture":"#0","tintindex":0},"up":{"uv":[0.0,0.0,0.0,1.8125],"rotation":0,"texture":"#0","tintindex":0},"west":{"uv":[8.75,0.75,6.9375,0.875],"rotation":0,"texture":"#0","tintindex":0}}}],"display":{"head":{"translation":[0.0,-6.4,51.989685],"rotation":[0.0,0.0,0.0],"scale":[3.8095,3.8095,3.8095]}}}